[	
    {"app": "Go/No-Go", "id": "0001", "message": "ERROR", "level": "Medium", "date": "09/18/2013"},
    {"app": "TM Viewer", "id": "1001", "message": "FAILURE", "level": "High","date": "09/18/2013"},
    {"app": "FOP Viewer", "id": "2001", "message": "WARNING", "level": "Medium", "date": "09/18/2013"},
    {"app": "FOP Viewer", "id": "2002", "message": "SUCCESS", "level": "Low","date": "09/19/2013"},
    {"app": "Go/No-Go", "id": "0002", "message": "ERROR", "level": "High", "date": "09/19/2013"},
    {"app": "TM Viewer", "id": "1002", "message": "FAILURE", "level": "Low","date": "09/19/2013"} 
]


